pyDMNrules/DMNrules.py
pyDMNrules/__init__.py
pydmnrules_mcp/__init__.py
pydmnrules_mcp/server.py
pyDMNrules_enhanced-1.6.0.dist-info/LICENSE
pyDMNrules_enhanced-1.6.0.dist-info/LICENSE_MCP
pyDMNrules_enhanced-1.6.0.dist-info/METADATA
pyDMNrules_enhanced-1.6.0.dist-info/WHEEL
pyDMNrules_enhanced-1.6.0.dist-info/top_level.txt
pyDMNrules_enhanced-1.6.0.dist-info/RECORD
