Metadata-Version: 2.1
Name: pyDMNrules-enhanced
Version: 1.6.0
Summary: Enhanced pyDMNrules with full DRD support (informationRequirement/requiredInput auto-mapping)
Home-page: https://github.com/uengine/pyDMNrules
Author: Russell McDonell (Enhanced by uengine)
Author-email: russell.mcdonell@c-cost.com
Classifier: Programming Language :: Python :: 3
Classifier: License :: OSI Approved :: GNU General Public License v3 (GPLv3)
Classifier: Operating System :: OS Independent
Requires-Python: >=3.6
License-File: LICENSE
License-File: LICENSE_MCP
Requires-Dist: datetime
Requires-Dist: pySFeel
Requires-Dist: openpyxl
Requires-Dist: pandas
